pypodcontrol/__init__.py
pypodcontrol/iapbase.py
pypodcontrol/iapclient.py
pypodcontrol/lingo/__init__.py
pypodcontrol/lingo/general.py
pypodcontrol/lingo/lingo.py
pypodcontrol/lingo/simpleremote.py
pypodcontrol-0.0a1.dist-info/METADATA
pypodcontrol-0.0a1.dist-info/WHEEL
pypodcontrol-0.0a1.dist-info/RECORD
