Metadata-Version: 2.4
Name: pyPodControl
Version: 0.0a1
Summary: Python implementation of iPod Accessory Protocol
Project-URL: Homepage, https://github.com/RaduTek/pyPodControl
Project-URL: Issues, https://github.com/RaduTek/pyPodControl/issues
Author-email: RaduTek <me@radutek.uk>
Requires-Dist: pyserial>=3.5
